chromatic/__init__.py
chromatic/__init__.pyi
chromatic/_typing.py
chromatic/_version.py
chromatic/demo.py
chromatic/color/__init__.py
chromatic/color/__init__.pyi
chromatic/color/colorconv.py
chromatic/color/core.py
chromatic/color/core.pyi
chromatic/color/iterators.py
chromatic/color/palette.py
chromatic/color/palette.pyi
chromatic/data/__init__.py
chromatic/data/__init__.pyi
chromatic/data/_fetchers.py
chromatic/data/butterfly.jpg
chromatic/data/escher.png
chromatic/data/goblin_virus.png
chromatic/data/registry.json
chromatic/data/userfont.py
chromatic/data/userfont.pyi
chromatic/data/userfont.schema.json
chromatic/data/fonts/consolas.ttf
chromatic/data/fonts/vga437.ttf
chromatic/image/__init__.py
chromatic/image/__init__.pyi
chromatic/image/_array.py
chromatic/image/_curses.py
chromatic/image/_glyph.py
chromatic_python-0.4.1.dist-info/licenses/LICENSE
chromatic_python-0.4.1.dist-info/METADATA
chromatic_python-0.4.1.dist-info/WHEEL
chromatic_python-0.4.1.dist-info/top_level.txt
chromatic_python-0.4.1.dist-info/RECORD
