Metadata-Version: 2.4
Name: chromatic-python
Version: 0.4.1
Summary: ANSI art image processing and colored terminal text
Author: crypt0lith
Project-URL: Homepage, https://github.com/crypt0lith/chromatic
Keywords: ansi,ascii,art,font,image,terminal,parser
Classifier: Programming Language :: Python :: 3.12
Classifier: Operating System :: OS Independent
Classifier: Topic :: Software Development :: Libraries :: Python Modules
Classifier: Typing :: Typed
Requires-Python: >=3.12
License-File: LICENSE
Requires-Dist: numpy<2.6,>=1.25.2
Requires-Dist: pillow!=11.2.*,<12.0,>=10.1
Requires-Dist: networkx<4.0,>=3.0
Requires-Dist: scipy<2.0,>=1.11.4
Requires-Dist: opencv-python
Requires-Dist: scikit-image
Requires-Dist: scikit-learn
Requires-Dist: fonttools
Requires-Dist: lazy_loader
Dynamic: license-file
